deepecho/__init__.py
deepecho/demo.py
deepecho/sequences.py
deepecho/data/demo.csv
deepecho/models/__init__.py
deepecho/models/base.py
deepecho/models/basic_gan.py
deepecho/models/par.py
deepecho-0.8.0.dist-info/licenses/LICENSE
deepecho-0.8.0.dist-info/METADATA
deepecho-0.8.0.dist-info/WHEEL
deepecho-0.8.0.dist-info/top_level.txt
deepecho-0.8.0.dist-info/RECORD
